wjyzcm/__init__.py
wjyzcm/config.py
wjyzcm-0.0.3.dist-info/METADATA
wjyzcm-0.0.3.dist-info/WHEEL
wjyzcm-0.0.3.dist-info/top_level.txt
wjyzcm-0.0.3.dist-info/RECORD
