Metadata-Version: 2.4
Name: wjyzcm
Version: 0.0.3
Summary: wjyzcm
Author-email: SnowRabbit <snowrabbit@snowrabbit.top>
License: MIT
Classifier: Development Status :: 3 - Alpha
Classifier: License :: OSI Approved :: MIT License
Classifier: Programming Language :: Python :: 3
Classifier: Programming Language :: Python :: 3.9
Classifier: Programming Language :: Python :: 3.10
Classifier: Programming Language :: Python :: 3.11
Classifier: Programming Language :: Python :: 3.12
Classifier: Operating System :: OS Independent
Requires-Python: <4.0,>=3.9
Requires-Dist: nonebot2>=2.0.0
Requires-Dist: nonebot-adapter-onebot>=2.0.0
